instanseg/__init__.py
instanseg/inference_class.py
instanseg/bioimageio_models/model-index.json
instanseg/scripts/inference.py
instanseg/scripts/test.py
instanseg/scripts/train.py
instanseg/utils/AI_utils.py
instanseg/utils/__init__.py
instanseg/utils/augmentation_config.py
instanseg/utils/augmentations.py
instanseg/utils/biological_utils.py
instanseg/utils/create_bioimageio_model.py
instanseg/utils/data_download.py
instanseg/utils/data_loader.py
instanseg/utils/metrics.py
instanseg/utils/model_loader.py
instanseg/utils/pytorch_utils.py
instanseg/utils/tiling.py
instanseg/utils/utils.py
instanseg/utils/visualization.py
instanseg/utils/loss/__init__.py
instanseg/utils/loss/instanseg_loss.py
instanseg/utils/loss/lovasz_losses.py
instanseg/utils/models/CellposeSam.py
instanseg/utils/models/ChannelInvariantNet.py
instanseg/utils/models/InstanSeg_UNet.py
instanseg/utils/models/__init__.py
instanseg/utils/models/sam.py
instanseg/utils/rdf_scripts/instanseg_postprocess.ijm
instanseg/utils/rdf_scripts/instanseg_preprocess.ijm
instanseg_torch-0.1.1.dist-info/METADATA
instanseg_torch-0.1.1.dist-info/WHEEL
instanseg_torch-0.1.1.dist-info/entry_points.txt
instanseg_torch-0.1.1.dist-info/licenses/LICENSE
instanseg_torch-0.1.1.dist-info/RECORD
