Metadata-Version: 2.4
Name: instanseg-torch
Version: 0.1.1
Summary: Package for instanseg-torch PyPi
Project-URL: Homepage, https://github.com/instanseg/instanseg
Project-URL: Issues, https://github.com/instanseg/instanseg/issues
Author-email: Thibaut Goldsborough <thibaut.golds@gmail.com>
License-File: LICENSE
Classifier: License :: OSI Approved :: Apache Software License
Classifier: Operating System :: OS Independent
Classifier: Programming Language :: Python :: 3
Requires-Python: >=3.9
Requires-Dist: einops>=0.6.0
Requires-Dist: fastremap>=1.14.0
Requires-Dist: matplotlib>=3.7.0
Requires-Dist: numpy>=1.24.0
Requires-Dist: requests>=2.0.0
Requires-Dist: scikit-image>=0.21.0
Requires-Dist: torch>=2.0.0
Requires-Dist: tqdm>=4.65.0
Provides-Extra: doc
Requires-Dist: sphinx-rtd-theme~=2.0.0; extra == 'doc'
Requires-Dist: sphinx~=7.4.5; extra == 'doc'
Provides-Extra: full
Requires-Dist: bioimageio-core>=0.9.0; extra == 'full'
Requires-Dist: bioimageio-spec>=0.5.6.0; extra == 'full'
Requires-Dist: bioio-ome-tiff>=1.0.0; extra == 'full'
Requires-Dist: bioio>=1.0.0; extra == 'full'
Requires-Dist: colorcet>=3.0.1; extra == 'full'
Requires-Dist: cucim>=23.10.00; (platform_system == 'Linux') and extra == 'full'
Requires-Dist: edt; extra == 'full'
Requires-Dist: geojson>=3.0.0; extra == 'full'
Requires-Dist: hyperopt>=0.2.7; extra == 'full'
Requires-Dist: imagecodecs>=2024.1.1; extra == 'full'
Requires-Dist: ipykernel>=6.28.0; extra == 'full'
Requires-Dist: ipywidgets>=8.1.1; extra == 'full'
Requires-Dist: jupyterlab>=4.0.10; extra == 'full'
Requires-Dist: kornia>=0.7.0; extra == 'full'
Requires-Dist: line-profiler>=4.1.3; extra == 'full'
Requires-Dist: monai>=1.3.0; extra == 'full'
Requires-Dist: onnx>=1.15.0; extra == 'full'
Requires-Dist: opencv-python>=4.9.0; extra == 'full'
Requires-Dist: palettable>=3.3.3; extra == 'full'
Requires-Dist: rasterio>=1.3.0; extra == 'full'
Requires-Dist: scikit-learn>=1.3.2; extra == 'full'
Requires-Dist: scipy>=1.11.4; extra == 'full'
Requires-Dist: seaborn>=0.13.1; extra == 'full'
Requires-Dist: slideio>=2.6.0; extra == 'full'
Requires-Dist: tensorboard>=2.17.0; extra == 'full'
Requires-Dist: tifffile>=2023.9.0; extra == 'full'
Requires-Dist: tiffslide>=2.4.0; extra == 'full'
Requires-Dist: tkinterdnd2>=0.4.2; extra == 'full'
Requires-Dist: torchstain>=1.3.0; extra == 'full'
Requires-Dist: torchvision>=0.15.0; extra == 'full'
Requires-Dist: zarr<3,>=2.0.0; extra == 'full'
Provides-Extra: io
Requires-Dist: bioio-ome-tiff>=1.0.0; extra == 'io'
Requires-Dist: bioio>=1.0.0; extra == 'io'
Requires-Dist: geojson>=3.0.0; extra == 'io'
Requires-Dist: rasterio>=1.3.0; extra == 'io'
Requires-Dist: slideio>=2.6.0; extra == 'io'
Requires-Dist: tifffile>=2023.9.0; extra == 'io'
Requires-Dist: tiffslide>=2.4.0; extra == 'io'
Requires-Dist: zarr<3,>=2.0.0; extra == 'io'
Provides-Extra: test
Requires-Dist: bioio-ome-tiff>=1.0.0; extra == 'test'
Requires-Dist: bioio-tifffile>=1.0.0; extra == 'test'
Requires-Dist: bioio>=1.0.0; extra == 'test'
Requires-Dist: coverage~=7.6.5; extra == 'test'
Requires-Dist: genbadge~=1.1.1; extra == 'test'
Requires-Dist: geojson>=3.0.0; extra == 'test'
Requires-Dist: pytest~=8.2.2; extra == 'test'
Requires-Dist: rasterio>=1.3.0; extra == 'test'
Requires-Dist: slideio>=2.6.0; extra == 'test'
Requires-Dist: tifffile>=2023.9.0; extra == 'test'
Requires-Dist: tiffslide>=2.4.0; extra == 'test'
Requires-Dist: zarr<3,>=2.0.0; extra == 'test'
